doodoo/__init__.py
doodoo-0.3.dist-info/METADATA
doodoo-0.3.dist-info/WHEEL
doodoo-0.3.dist-info/top_level.txt
doodoo-0.3.dist-info/RECORD
