Metadata-Version: 2.1
Name: doodoo
Version: 0.3
Summary: The new pop(0)
Home-page: https://github.com/MiTo0o
Author: MiTo
Author-email: derzanchiang1800@gmail.com
License: MIT
Platform: UNKNOWN
